torch_flops/__init__.py
torch_flops/flops_engine.py
torch_flops/flops_ops.py
torch_flops-0.4.1.data/data/README.md
torch_flops-0.4.1.dist-info/LICENCE
torch_flops-0.4.1.dist-info/METADATA
torch_flops-0.4.1.dist-info/WHEEL
torch_flops-0.4.1.dist-info/top_level.txt
torch_flops-0.4.1.dist-info/RECORD
