Metadata-Version: 2.1
Name: torch_flops
Version: 0.4.1
Summary: A library for calculating the FLOPs in the forward() process based on torch.fx
Home-page: https://github.com/zugexiaodui/torch_flops
Author: Yue Lu
Author-email: luyue163@126.com
License: MIT License
Requires: python(>=3.8)
Requires: torch(>=2.0)
Requires: tabulate
License-File: LICENCE
